collective.transform.xtags-0.1-py2.7-nspkg.pth
collective/transform/xtags/__init__.py
collective/transform/xtags/behavior.py
collective/transform/xtags/events.py
collective/transform/xtags/factories.py
collective/transform/xtags/quark_tagged_text.py
collective/transform/xtags/setuphandlers.py
collective/transform/xtags/browser/__init__.py
collective/transform/xtags/browser/views.py
collective/transform/xtags/widgets/__init__.py
collective/transform/xtags/widgets/widget.py
collective.transform.xtags-0.1.dist-info/METADATA
collective.transform.xtags-0.1.dist-info/RECORD
collective.transform.xtags-0.1.dist-info/WHEEL
collective.transform.xtags-0.1.dist-info/entry_points.txt
collective.transform.xtags-0.1.dist-info/namespace_packages.txt
collective.transform.xtags-0.1.dist-info/top_level.txt
