Metadata-Version: 2.1
Name: collective.transform.xtags
Version: 0.1
Summary: Transform xtags to HTML
Home-page: https://github.com/espenmn/collective.transform.xtags
Author: Espen Moe-Nilssen
Author-email: espen@medialog.no
License: GPL
Platform: UNKNOWN
Classifier: Framework :: Plone
Classifier: Framework :: Plone :: 5.0
Classifier: Programming Language :: Python
Classifier: Topic :: Software Development :: Libraries :: Python Modules
Classifier: Topic :: Text Processing
Requires-Dist: setuptools
Requires-Dist: collective.dexteritytextindexer
Requires-Dist: plone.autoform
Requires-Dist: plone.directives.form
Requires-Dist: plone.supermodel
Requires-Dist: pypeg2
